half_adder.v
module half_adder(a, b, Sum, Carry);
	input a, b;
	output Sum, Carry;
	
	xor (Sum, a, b);
	and (Carry, a, b);
endmodule

full_adder.v
module full_adder(input a, b, c, output Sum, Carry);
	wire w1, w2, w3;
	half_adder HA1(a, b, w1, w2);
	half_adder HA2(c, w1, Sum, w3);
	or G1(Carry, w2, w2, w3);
endmodule

full_adder_tb.v
module full_adder_tb;
	reg a, b, c;
	wire Sum, Carry;
	
	full_adder u0(a, b, c, Sum, Carry);
	
	initial begin
		$monitor("At time %0t: a=%b b=%b Sum=%b Carry=%b", $time, a, b, Sum, Carry);
		$dumpfile("_A02a.vcd");
		$dumpvars(0,full_adder_tb);
		
		{a, b, c}=0;
		#2 a = 0; b = 0; c = 0;
		#2 a = 0; b = 0; c = 1;
		#2 a = 0; b = 1; c = 0;
		#2 a = 0; b = 1; c = 1;
		#2 a = 1; b = 0; c = 0;
		#2 a = 1; b = 0; c = 1;
		#2 a = 1; b = 1; c = 0;
		#2 a = 1; b = 1; c = 1;
		
		#2 $finish;
	end
endmodule

_A02a (1).vcd
$date
	Sat Apr 20 10:53:36 2024
$end
$version
	Icarus Verilog
$end
$timescale
	1s
$end
$scope module full_adder_tb $end
$var wire 1 ! Sum $end
$var wire 1 " Carry $end
$var reg 1 # a $end
$var reg 1 $ b $end
$var reg 1 % c $end
$scope module u0 $end
$var wire 1 " Carry $end
$var wire 1 # a $end
$var wire 1 $ b $end
$var wire 1 % c $end
$var wire 1 & w3 $end
$var wire 1 ' w2 $end
$var wire 1 ( w1 $end
$var wire 1 ! Sum $end
$scope module HA1 $end
$var wire 1 ' Carry $end
$var wire 1 ( Sum $end
$var wire 1 # a $end
$var wire 1 $ b $end
$upscope $end
$scope module HA2 $end
$var wire 1 & Carry $end
$var wire 1 ! Sum $end
$var wire 1 % a $end
$var wire 1 ( b $end
$upscope $end
$upscope $end
$upscope $end
$enddefinitions $end
#0
$dumpvars
0(
0'
0&
0%
0$
0#
0"
0!
$end
#4
1!
1%
#6
1(
0%
1$
#8
1"
0!
1&
1%
#10
0"
1!
0&
0%
0$
1#
#12
1"
0!
1&
1%
#14
0&
0(
1'
0%
1$
#16
1!
1%
