Copy of expression_test.v
module expression_test(input a, b, c, output op);
	
	wire x1, x2;
	
	// A + B . C
	assign op = a|b&c;
	
	// A' . B + C' . B
	//assign op = ~ a & b | ~ c & b;
	
	// (X + Y) Z'
	//xor (op, a|b, c);
	
	and(x1, a, b);
	xor(x2, a, c);
	//xnor(op, x1, x2);

endmodule

expression_test_tb.v
module expression_test_tb;
	reg a1, a2, a3;
	wire b;
	expression_test g0(a1, a2, a3, b);
	initial begin
		$monitor("At time %0t: a1=%b a2=%b a3=%b  or[a1,a2] and[a2,a3]=%b", $time, a1, a2, a3, b);
		$dumpfile("_A02a.vcd");
		$dumpvars(0,expression_test_tb);
		
		a1 = 0; a2 = 0; a3 = 0;
		#2 a1 = 0; a2 = 0; a3 = 0;
		#2 a1 = 0; a2 = 0; a3 = 1;
		#2 a1 = 0; a2 = 1; a3 = 0;
		#2 a1 = 0; a2 = 1; a3 = 1;
		#2 a1 = 1; a2 = 0; a3 = 0;
		#2 a1 = 1; a2 = 0; a3 = 1;
		#2 a1 = 1; a2 = 1; a3 = 0;
		#2 a1 = 1; a2 = 1; a3 = 1;
		#2 $finish;
	end
endmodule

_A02a.vcd
$date
	Sun Jun  2 16:32:03 2024
$end
$version
	Icarus Verilog
$end
$timescale
	1s
$end
$scope module expression_test_tb $end
$var wire 1 ! b $end
$var reg 1 " a1 $end
$var reg 1 # a2 $end
$var reg 1 $ a3 $end
$scope module g0 $end
$var wire 1 " a $end
$var wire 1 # b $end
$var wire 1 $ c $end
$var wire 1 ! op $end
$var wire 1 % x1 $end
$var wire 1 & x2 $end
$upscope $end
$upscope $end
$enddefinitions $end
$comment Show the parameter values. $end
$dumpall
$end
#0
$dumpvars
0&
0%
0$
0#
0"
0!
$end
#4
1&
1$
#6
0&
0$
1#
#8
1!
1&
1$
#10
0$
0#
1"
#12
0&
1$
#14
1&
1%
0$
1#
#16
0&
1$
