Copy of half_subtractor.v
module half_subtractor(A, B, Difference, Borrow);
	input A, B;
	output Difference, Borrow;
	xor(Difference, A, B);
	and(Borrow, ~A, B);
endmodule

Copy of full_subtractor.v
module full_subtractor (input A, B, Bin, output Difference, Borrow);
	wire w1, w2, w3;
	half_subtractor HS1(A, B, w1, w2);
	half_subtractor HS2(Bin, w1, Difference, w3);
	or G1(Borrow, w2,w3);
endmodule

full_subtractor_tb.v
module full_subtractor_tb;
	reg A, B, Bin;
	wire Difference, Borrow;
	full_subtractor u0(A, B, Bin, Difference, Borrow);
	
	initial begin
		$monitor("At time %0t: A=%B B=%B Bin=%B Difference=%B Borrow=%B", $time, A, B, Bin, Difference, Borrow);
		$dumpfile("full_subtractor.vcd"); 
		$dumpvars(0, full_subtractor_tb);
		
		{A, B, Bin} = 0;
		#2 A=0; B=0; Bin=0;
		#2 A=0; B=0; Bin=1;
		#2 A=0; B=1; Bin=0;
		#2 A=0; B=1; Bin=1;
		#2 A=1; B=0; Bin=0;
		#2 A=1; B=0; Bin=1;
		#2 A=1; B=1; Bin=0;
		#2 A=1; B=1; Bin=1;
		#2 $finish;
	end
endmodule

full_subtractor.vcd
$date
	Tue Jun  4 10:47:02 2024
$end
$version
	Icarus Verilog
$end
$timescale
	1s
$end
$scope module full_subtractor_tb $end
$var wire 1 ! Difference $end
$var wire 1 " Borrow $end
$var reg 1 # A $end
$var reg 1 $ B $end
$var reg 1 % Bin $end
$scope module u0 $end
$var wire 1 # A $end
$var wire 1 $ B $end
$var wire 1 % Bin $end
$var wire 1 " Borrow $end
$var wire 1 & w3 $end
$var wire 1 ' w2 $end
$var wire 1 ( w1 $end
$var wire 1 ! Difference $end
$scope module HS1 $end
$var wire 1 # A $end
$var wire 1 $ B $end
$var wire 1 ' Borrow $end
$var wire 1 ( Difference $end
$upscope $end
$scope module HS2 $end
$var wire 1 % A $end
$var wire 1 ( B $end
$var wire 1 & Borrow $end
$var wire 1 ! Difference $end
$upscope $end
$upscope $end
$upscope $end
$enddefinitions $end
$comment Show the parameter values. $end
$dumpall
$end
#0
$dumpvars
0(
0'
0&
0%
0$
0#
0"
0!
$end
#4
1!
1%
#6
1&
1"
1(
1'
0%
1$
#8
0&
0!
1%
#10
1&
1"
1!
0'
0%
0$
1#
#12
0"
0&
0!
1%
#14
0(
0%
1$
#16
1!
1%
